{
  "status": "running",
  "generation": 5,
  "games_completed": 8221000,
  "games_total": 36000000,
  "pct_complete": 22.8,
  "games_per_sec": 160.9,
  "batch_gps": 289.4,
  "eta_minutes": 2877.0,
  "checkpoint_file": "C:\\Users\\bill\\Downloads\\crossplay\\crossplay\\superleaves\\gen5_8221000.pkl",
  "leave_table_size": 921298,
  "timestamp": "2026-03-06 08:02:59",
  "single_tile_values": {
    "S": 23.43,
    "I": 19.56,
    "A": 18.5,
    "E": 17.44,
    "N": 16.84,
    "?": 15.49,
    "T": 15.22,
    "R": 14.63,
    "O": 14.41,
    "Y": 13.19,
    "U": 12.69,
    "M": 11.53,
    "H": 11.47,
    "G": 11.17,
    "K": 10.93,
    "F": 10.7,
    "D": 10.57,
    "W": 10.46,
    "B": 10.31,
    "P": 9.87,
    "L": 9.54,
    "C": 9.48,
    "X": 7.18,
    "J": 5.72,
    "Z": 3.39,
    "V": 2.23,
    "Q": 0.98
  }
}